blox/__init__.py
blox/client.py
blox/exceptions.py
blox/web.py
blox/api_types/__init__.py
blox/api_types/web_types/__init__.py
blox/api_types/web_types/_shared.py
blox/api_types/web_types/avatar.py
blox/api_types/web_types/groups.py
blox/api_types/web_types/thumbnails.py
blox/api_types/web_types/users.py
blox/models/__init__.py
blox/models/groups.py
blox/models/thumbnails.py
blox/models/users.py
blox/utility/__init__.py
blox/utility/cache.py
blox/utility/enum.py
blox/utility/iterators.py
blox/utility/requests.py
blox_api-0.0.1.dist-info/licenses/LICENSE
blox_api-0.0.1.dist-info/METADATA
blox_api-0.0.1.dist-info/WHEEL
blox_api-0.0.1.dist-info/top_level.txt
blox_api-0.0.1.dist-info/RECORD
